{"type":"FeatureCollection","features":[
{"type":"Feature","geometry":{"type":"LineString","coordinates":[[139.08166,37.908],[139.08217,37.9073]]},"properties":{"N02_001":"11","N02_002":"2","N02_003":"???","N02_004":"???????"}},
{"type":"Feature","geometry":{"type":"LineString","coordinates":[[139.06475,37.91297],[139.07349,37.91498],[139.07804,37.91337],[139.08166,37.908]]},"properties":{"N02_001":"11","N02_002":"2","N02_003":"???","N02_004":"???????"}},
{"type":"Feature","geometry":{"type":"LineString","coordinates":[[139.06246,37.91271],[139.06475,37.91297]]},"properties":{"N02_001":"11","N02_002":"2","N02_003":"???","N02_004":"???????"}},
{"type":"Feature","geometry":{"type":"LineString","coordinates":[[139.06251,37.91254],[139.06475,37.91297]]},"properties":{"N02_001":"11","N02_002":"2","N02_003":"???","N02_004":"???????"}},
{"type":"Feature","geometry":{"type":"LineString","coordinates":[[139.08166,37.908],[139.08592,37.90449]]},"properties":{"N02_001":"11","N02_002":"2","N02_003":"???","N02_004":"???????"}},
{"type":"Feature","geometry":{"type":"LineString","coordinates":[[139.05944,37.91178],[139.06251,37.91254]]},"properties":{"N02_001":"11","N02_002":"2","N02_003":"???","N02_004":"???????"}},
{"type":"Feature","geometry":{"type":"LineString","coordinates":[[139.06246,37.91271],[139.05939,37.91195]]},"properties":{"N02_001":"11","N02_002":"2","N02_003":"???","N02_004":"???????"}},
{"type":"Feature","geometry":{"type":"LineString","coordinates":[[139.09481,37.89692],[139.09353,37.89795]]},"properties":{"N02_001":"11","N02_002":"2","N02_003":"???","N02_004":"???????"}},
{"type":"Feature","geometry":{"type":"LineString","coordinates":[[139.12122,37.79892],[139.1212,37.80168]]},"properties":{"N02_001":"11","N02_002":"2","N02_003":"???","N02_004":"???????"}},
{"type":"Feature","geometry":{"type":"LineString","coordinates":[[139.12122,37.79892],[139.12125,37.79643]]},"properties":{"N02_001":"11","N02_002":"2","N02_003":"???","N02_004":"???????"}},
{"type":"Feature","geometry":{"type":"LineString","coordinates":[[139.10743,37.87868],[139.10045,37.89144],[139.09614,37.89581]]},"properties":{"N02_001":"11","N02_002":"2","N02_003":"???","N02_004":"???????"}},
{"type":"Feature","geometry":{"type":"LineString","coordinates":[[139.11776,37.81222],[139.11695,37.81398]]},"properties":{"N02_001":"11","N02_002":"2","N02_003":"???","N02_004":"???????"}},
{"type":"Feature","geometry":{"type":"LineString","coordinates":[[139.08217,37.9073],[139.08657,37.90355]]},"properties":{"N02_001":"11","N02_002":"2","N02_003":"???","N02_004":"???????"}},
{"type":"Feature","geometry":{"type":"LineString","coordinates":[[139.09472,37.74787],[139.09626,37.74989]]},"properties":{"N02_001":"11","N02_002":"2","N02_003":"???","N02_004":"???????"}},
{"type":"Feature","geometry":{"type":"LineString","coordinates":[[139.07512,37.71988],[139.08144,37.73121],[139.08991,37.74142],[139.09472,37.74787]]},"properties":{"N02_001":"11","N02_002":"2","N02_003":"???","N02_004":"???????"}},
{"type":"Feature","geometry":{"type":"LineString","coordinates":[[139.06037,37.69285],[139.06102,37.69444]]},"properties":{"N02_001":"11","N02_002":"2","N02_003":"???","N02_004":"???????"}},
{"type":"Feature","geometry":{"type":"LineString","coordinates":[[139.08592,37.90449],[139.08657,37.90355]]},"properties":{"N02_001":"11","N02_002":"2","N02_003":"???","N02_004":"???????"}},
{"type":"Feature","geometry":{"type":"LineString","coordinates":[[139.11412,37.7725],[139.11479,37.7735]]},"properties":{"N02_001":"11","N02_002":"2","N02_003":"???","N02_004":"???????"}},
{"type":"Feature","geometry":{"type":"LineString","coordinates":[[139.11145,37.83348],[139.11042,37.83907],[139.11287,37.86725],[139.10905,37.87569]]},"properties":{"N02_001":"11","N02_002":"2","N02_003":"???","N02_004":"???????"}},
{"type":"Feature","geometry":{"type":"LineString","coordinates":[[139.11695,37.81398],[139.11414,37.82024],[139.11181,37.83168]]},"properties":{"N02_001":"11","N02_002":"2","N02_003":"???","N02_004":"???????"}},
{"type":"Feature","geometry":{"type":"LineString","coordinates":[[139.09614,37.89581],[139.09481,37.89692]]},"properties":{"N02_001":"11","N02_002":"2","N02_003":"???","N02_004":"???????"}},
{"type":"Feature","geometry":{"type":"LineString","coordinates":[[139.09353,37.89795],[139.08657,37.90355]]},"properties":{"N02_001":"11","N02_002":"2","N02_003":"???","N02_004":"???????"}},
{"type":"Feature","geometry":{"type":"LineString","coordinates":[[139.06102,37.69444],[139.0655,37.70498],[139.07402,37.71817]]},"properties":{"N02_001":"11","N02_002":"2","N02_003":"???","N02_004":"???????"}},
{"type":"Feature","geometry":{"type":"LineString","coordinates":[[139.11479,37.7735],[139.12099,37.78279],[139.12125,37.79643]]},"properties":{"N02_001":"11","N02_002":"2","N02_003":"???","N02_004":"???????"}},
{"type":"Feature","geometry":{"type":"LineString","coordinates":[[139.09626,37.74989],[139.10845,37.76659],[139.11412,37.7725]]},"properties":{"N02_001":"11","N02_002":"2","N02_003":"???","N02_004":"???????"}},
{"type":"Feature","geometry":{"type":"LineString","coordinates":[[139.1212,37.80168],[139.12119,37.80463]]},"properties":{"N02_001":"11","N02_002":"2","N02_003":"???","N02_004":"???????"}},
{"type":"Feature","geometry":{"type":"LineString","coordinates":[[139.12119,37.80463],[139.11776,37.81222]]},"properties":{"N02_001":"11","N02_002":"2","N02_003":"???","N02_004":"???????"}},
{"type":"Feature","geometry":{"type":"LineString","coordinates":[[139.11181,37.83168],[139.11145,37.83348]]},"properties":{"N02_001":"11","N02_002":"2","N02_003":"???","N02_004":"???????"}},
{"type":"Feature","geometry":{"type":"LineString","coordinates":[[139.10905,37.87569],[139.10743,37.87868]]},"properties":{"N02_001":"11","N02_002":"2","N02_003":"???","N02_004":"???????"}},
{"type":"Feature","geometry":{"type":"LineString","coordinates":[[139.07402,37.71817],[139.07512,37.71988]]},"properties":{"N02_001":"11","N02_002":"2","N02_003":"???","N02_004":"???????"}},
{"type":"Feature","geometry":{"type":"LineString","coordinates":[[138.85322,37.44585],[138.85147,37.4414]]},"properties":{"N02_001":"11","N02_002":"2","N02_003":"???","N02_004":"???????"}},
{"type":"Feature","geometry":{"type":"LineString","coordinates":[[138.9291,37.57379],[138.92802,37.57222]]},"properties":{"N02_001":"11","N02_002":"2","N02_003":"???","N02_004":"???????"}},
{"type":"Feature","geometry":{"type":"LineString","coordinates":[[138.88178,37.50587],[138.88065,37.50401]]},"properties":{"N02_001":"11","N02_002":"2","N02_003":"???","N02_004":"???????"}},
{"type":"Feature","geometry":{"type":"LineString","coordinates":[[138.90325,37.53792],[138.90638,37.54247]]},"properties":{"N02_001":"11","N02_002":"2","N02_003":"???","N02_004":"???????"}},
{"type":"Feature","geometry":{"type":"LineString","coordinates":[[138.92802,37.57222],[138.90638,37.54247]]},"properties":{"N02_001":"11","N02_002":"2","N02_003":"???","N02_004":"???????"}},
{"type":"Feature","geometry":{"type":"LineString","coordinates":[[139.04976,37.65978],[139.04815,37.65791]]},"properties":{"N02_001":"11","N02_002":"2","N02_003":"???","N02_004":"???????"}},
{"type":"Feature","geometry":{"type":"LineString","coordinates":[[138.78529,37.39707],[138.80563,37.39515],[138.81286,37.39488]]},"properties":{"N02_001":"11","N02_002":"2","N02_003":"???","N02_004":"???????"}},
{"type":"Feature","geometry":{"type":"LineString","coordinates":[[138.75678,37.38716],[138.75997,37.39064],[138.77285,37.39754],[138.78202,37.3974]]},"properties":{"N02_001":"11","N02_002":"2","N02_003":"???","N02_004":"???????"}},
{"type":"Feature","geometry":{"type":"LineString","coordinates":[[139.01537,37.63959],[139.014,37.63902]]},"properties":{"N02_001":"11","N02_002":"2","N02_003":"???","N02_004":"???????"}},
{"type":"Feature","geometry":{"type":"LineString","coordinates":[[138.90554,37.54122],[138.90411,37.53908]]},"properties":{"N02_001":"11","N02_002":"2","N02_003":"???","N02_004":"???????"}},
{"type":"Feature","geometry":{"type":"LineString","coordinates":[[138.88178,37.50587],[138.88983,37.51946],[138.90325,37.53792]]},"properties":{"N02_001":"11","N02_002":"2","N02_003":"???","N02_004":"???????"}},
{"type":"Feature","geometry":{"type":"LineString","coordinates":[[138.73098,37.35563],[138.73752,37.35891],[138.74294,37.35925],[138.74836,37.36272],[138.74977,37.36575],[138.74904,37.36892],[138.75133,37.37333],[138.75591,37.3852]]},"properties":{"N02_001":"11","N02_002":"2","N02_003":"???","N02_004":"???????"}},
{"type":"Feature","geometry":{"type":"LineString","coordinates":[[138.86199,37.4677],[138.85473,37.44968]]},"properties":{"N02_001":"11","N02_002":"2","N02_003":"???","N02_004":"???????"}},
{"type":"Feature","geometry":{"type":"LineString","coordinates":[[139.04815,37.65791],[139.03943,37.65333],[139.03016,37.64585],[139.01537,37.63959]]},"properties":{"N02_001":"11","N02_002":"2","N02_003":"???","N02_004":"???????"}},
{"type":"Feature","geometry":{"type":"LineString","coordinates":[[138.96064,37.62036],[138.95928,37.61586],[138.94368,37.59404]]},"properties":{"N02_001":"11","N02_002":"2","N02_003":"???","N02_004":"???????"}},
{"type":"Feature","geometry":{"type":"LineString","coordinates":[[138.82054,37.39757],[138.82339,37.40115]]},"properties":{"N02_001":"11","N02_002":"2","N02_003":"???","N02_004":"???????"}},
{"type":"Feature","geometry":{"type":"LineString","coordinates":[[138.86285,37.46995],[138.86199,37.4677]]},"properties":{"N02_001":"11","N02_002":"2","N02_003":"???","N02_004":"???????"}},
{"type":"Feature","geometry":{"type":"LineString","coordinates":[[138.82441,37.40238],[138.83528,37.41594]]},"properties":{"N02_001":"11","N02_002":"2","N02_003":"???","N02_004":"???????"}},
{"type":"Feature","geometry":{"type":"LineString","coordinates":[[139.014,37.63902],[139.00705,37.63618],[138.97668,37.629]]},"properties":{"N02_001":"11","N02_002":"2","N02_003":"???","N02_004":"???????"}},
{"type":"Feature","geometry":{"type":"LineString","coordinates":[[138.94368,37.59404],[138.94222,37.59202]]},"properties":{"N02_001":"11","N02_002":"2","N02_003":"???","N02_004":"???????"}},
{"type":"Feature","geometry":{"type":"LineString","coordinates":[[138.88065,37.50401],[138.86912,37.48463],[138.86285,37.46995]]},"properties":{"N02_001":"11","N02_002":"2","N02_003":"???","N02_004":"???????"}},
{"type":"Feature","geometry":{"type":"LineString","coordinates":[[138.84468,37.42755],[138.85016,37.43975],[138.85147,37.4414]]},"properties":{"N02_001":"11","N02_002":"2","N02_003":"???","N02_004":"???????"}},
{"type":"Feature","geometry":{"type":"LineString","coordinates":[[138.85473,37.44968],[138.85322,37.44585]]},"properties":{"N02_001":"11","N02_002":"2","N02_003":"???","N02_004":"???????"}},
{"type":"Feature","geometry":{"type":"LineString","coordinates":[[138.97668,37.629],[138.97283,37.62809]]},"properties":{"N02_001":"11","N02_002":"2","N02_003":"???","N02_004":"???????"}},
{"type":"Feature","geometry":{"type":"LineString","coordinates":[[138.97283,37.62809],[138.97066,37.62757]]},"properties":{"N02_001":"11","N02_002":"2","N02_003":"???","N02_004":"???????"}},
{"type":"Feature","geometry":{"type":"LineString","coordinates":[[138.97066,37.62757],[138.96442,37.62605],[138.96112,37.6221]]},"properties":{"N02_001":"11","N02_002":"2","N02_003":"???","N02_004":"???????"}},
{"type":"Feature","geometry":{"type":"LineString","coordinates":[[138.82339,37.40115],[138.82441,37.40238]]},"properties":{"N02_001":"11","N02_002":"2","N02_003":"???","N02_004":"???????"}},
{"type":"Feature","geometry":{"type":"LineString","coordinates":[[138.90554,37.54122],[138.90638,37.54247]]},"properties":{"N02_001":"11","N02_002":"2","N02_003":"???","N02_004":"???????"}},
{"type":"Feature","geometry":{"type":"LineString","coordinates":[[138.81286,37.39488],[138.81621,37.39479],[138.82054,37.39757]]},"properties":{"N02_001":"11","N02_002":"2","N02_003":"???","N02_004":"???????"}},
{"type":"Feature","geometry":{"type":"LineString","coordinates":[[138.75591,37.3852],[138.75678,37.38716]]},"properties":{"N02_001":"11","N02_002":"2","N02_003":"???","N02_004":"???????"}},
{"type":"Feature","geometry":{"type":"LineString","coordinates":[[138.84468,37.42755],[138.85012,37.43617],[138.85147,37.4414]]},"properties":{"N02_001":"11","N02_002":"2","N02_003":"???","N02_004":"???????"}},
{"type":"Feature","geometry":{"type":"LineString","coordinates":[[138.78202,37.3974],[138.78529,37.39707]]},"properties":{"N02_001":"11","N02_002":"2","N02_003":"???","N02_004":"???????"}},
{"type":"Feature","geometry":{"type":"LineString","coordinates":[[138.90411,37.53908],[138.90325,37.53792]]},"properties":{"N02_001":"11","N02_002":"2","N02_003":"???","N02_004":"???????"}},
{"type":"Feature","geometry":{"type":"LineString","coordinates":[[138.84078,37.423],[138.84468,37.42755]]},"properties":{"N02_001":"11","N02_002":"2","N02_003":"???","N02_004":"???????"}},
{"type":"Feature","geometry":{"type":"LineString","coordinates":[[138.96112,37.6221],[138.96064,37.62036]]},"properties":{"N02_001":"11","N02_002":"2","N02_003":"???","N02_004":"???????"}},
{"type":"Feature","geometry":{"type":"LineString","coordinates":[[138.81286,37.39488],[138.8175,37.39548],[138.82054,37.39757]]},"properties":{"N02_001":"11","N02_002":"2","N02_003":"???","N02_004":"???????"}},
{"type":"Feature","geometry":{"type":"LineString","coordinates":[[138.94222,37.59202],[138.9291,37.57379]]},"properties":{"N02_001":"11","N02_002":"2","N02_003":"???","N02_004":"???????"}},
{"type":"Feature","geometry":{"type":"LineString","coordinates":[[139.04976,37.65978],[139.05495,37.66579],[139.05586,37.66825],[139.05504,37.67282],[139.05849,37.67829],[139.05806,37.68737],[139.06037,37.69285]]},"properties":{"N02_001":"11","N02_002":"2","N02_003":"???","N02_004":"???????"}},
{"type":"Feature","geometry":{"type":"LineString","coordinates":[[138.83946,37.42127],[138.83763,37.41889]]},"properties":{"N02_001":"11","N02_002":"2","N02_003":"???","N02_004":"???????"}},
{"type":"Feature","geometry":{"type":"LineString","coordinates":[[138.84078,37.423],[138.83946,37.42127]]},"properties":{"N02_001":"11","N02_002":"2","N02_003":"???","N02_004":"???????"}},
{"type":"Feature","geometry":{"type":"LineString","coordinates":[[138.83528,37.41594],[138.83763,37.41889]]},"properties":{"N02_001":"11","N02_002":"2","N02_003":"???","N02_004":"???????"}},
{"type":"Feature","geometry":{"type":"LineString","coordinates":[[138.73098,37.35563],[138.7289,37.35467]]},"properties":{"N02_001":"11","N02_002":"2","N02_003":"???","N02_004":"???????"}},
{"type":"Feature","geometry":{"type":"LineString","coordinates":[[138.48695,37.34651],[138.49872,37.35145],[138.50604,37.35309],[138.51057,37.35522],[138.51632,37.35566]]},"properties":{"N02_001":"11","N02_002":"2","N02_003":"???","N02_004":"???????"}},
{"type":"Feature","geometry":{"type":"LineString","coordinates":[[138.58618,37.35726],[138.58731,37.35684]]},"properties":{"N02_001":"11","N02_002":"2","N02_003":"???","N02_004":"???????"}},
{"type":"Feature","geometry":{"type":"LineString","coordinates":[[138.33915,37.23357],[138.33175,37.22734],[138.32514,37.22298]]},"properties":{"N02_001":"11","N02_002":"2","N02_003":"???","N02_004":"???????"}},
{"type":"Feature","geometry":{"type":"LineString","coordinates":[[138.24673,37.17282],[138.2506,37.17396]]},"properties":{"N02_001":"11","N02_002":"2","N02_003":"???","N02_004":"???????"}},
{"type":"Feature","geometry":{"type":"LineString","coordinates":[[138.66227,37.3574],[138.66018,37.35732]]},"properties":{"N02_001":"11","N02_002":"2","N02_003":"???","N02_004":"???????"}},
{"type":"Feature","geometry":{"type":"LineString","coordinates":[[138.63757,37.33892],[138.63642,37.33767]]},"properties":{"N02_001":"11","N02_002":"2","N02_003":"???","N02_004":"???????"}},
{"type":"Feature","geometry":{"type":"LineString","coordinates":[[138.56166,37.36426],[138.56726,37.36441],[138.58618,37.35726]]},"properties":{"N02_001":"11","N02_002":"2","N02_003":"???","N02_004":"???????"}},
{"type":"Feature","geometry":{"type":"LineString","coordinates":[[138.55804,37.36378],[138.56166,37.36426]]},"properties":{"N02_001":"11","N02_002":"2","N02_003":"???","N02_004":"???????"}},
{"type":"Feature","geometry":{"type":"LineString","coordinates":[[138.48695,37.34651],[138.48552,37.34587]]},"properties":{"N02_001":"11","N02_002":"2","N02_003":"???","N02_004":"???????"}},
{"type":"Feature","geometry":{"type":"LineString","coordinates":[[138.48552,37.34587],[138.47921,37.3429],[138.46825,37.33603]]},"properties":{"N02_001":"11","N02_002":"2","N02_003":"???","N02_004":"???????"}},
{"type":"Feature","geometry":{"type":"LineString","coordinates":[[138.2506,37.17396],[138.26124,37.17701],[138.2639,37.1786],[138.26759,37.18335]]},"properties":{"N02_001":"11","N02_002":"2","N02_003":"???","N02_004":"???????"}},
{"type":"Feature","geometry":{"type":"LineString","coordinates":[[138.63642,37.33767],[138.63144,37.3341],[138.6204,37.33534],[138.6126,37.34078]]},"properties":{"N02_001":"11","N02_002":"2","N02_003":"???","N02_004":"???????"}},
{"type":"Feature","geometry":{"type":"LineString","coordinates":[[138.24673,37.17282],[138.2506,37.17396]]},"properties":{"N02_001":"11","N02_002":"2","N02_003":"???","N02_004":"???????"}},
{"type":"Feature","geometry":{"type":"LineString","coordinates":[[138.51839,37.35604],[138.52577,37.36007],[138.53112,37.36076],[138.53666,37.36266],[138.54243,37.36136],[138.54764,37.36143],[138.5548,37.36333]]},"properties":{"N02_001":"11","N02_002":"2","N02_003":"???","N02_004":"???????"}},
{"type":"Feature","geometry":{"type":"LineString","coordinates":[[138.46825,37.33603],[138.46623,37.33557]]},"properties":{"N02_001":"11","N02_002":"2","N02_003":"???","N02_004":"???????"}},
{"type":"Feature","geometry":{"type":"LineString","coordinates":[[138.34065,37.23484],[138.33915,37.23357]]},"properties":{"N02_001":"11","N02_002":"2","N02_003":"???","N02_004":"???????"}},
{"type":"Feature","geometry":{"type":"LineString","coordinates":[[138.31063,37.21397],[138.31681,37.21765]]},"properties":{"N02_001":"11","N02_002":"2","N02_003":"???","N02_004":"???????"}},
{"type":"Feature","geometry":{"type":"LineString","coordinates":[[138.43235,37.31754],[138.43057,37.31617]]},"properties":{"N02_001":"11","N02_002":"2","N02_003":"???","N02_004":"???????"}},
{"type":"Feature","geometry":{"type":"LineString","coordinates":[[138.3623,37.25288],[138.36106,37.25188]]},"properties":{"N02_001":"11","N02_002":"2","N02_003":"???","N02_004":"???????"}},
{"type":"Feature","geometry":{"type":"LineString","coordinates":[[138.58731,37.35684],[138.59828,37.35251],[138.61173,37.34147]]},"properties":{"N02_001":"11","N02_002":"2","N02_003":"???","N02_004":"???????"}},
{"type":"Feature","geometry":{"type":"LineString","coordinates":[[138.38539,37.27707],[138.37579,37.2643],[138.3623,37.25288]]},"properties":{"N02_001":"11","N02_002":"2","N02_003":"???","N02_004":"???????"}},
{"type":"Feature","geometry":{"type":"LineString","coordinates":[[138.6836,37.36686],[138.67902,37.36878],[138.673,37.36743],[138.66897,37.36065],[138.66556,37.358],[138.66227,37.3574]]},"properties":{"N02_001":"11","N02_002":"2","N02_003":"???","N02_004":"???????"}},
{"type":"Feature","geometry":{"type":"LineString","coordinates":[[138.51632,37.35566],[138.51839,37.35604]]},"properties":{"N02_001":"11","N02_002":"2","N02_003":"???","N02_004":"???????"}},
{"type":"Feature","geometry":{"type":"LineString","coordinates":[[138.30925,37.21289],[138.31681,37.21765]]},"properties":{"N02_001":"11","N02_002":"2","N02_003":"???","N02_004":"???????"}},
{"type":"Feature","geometry":{"type":"LineString","coordinates":[[138.32514,37.22298],[138.32449,37.22258]]},"properties":{"N02_001":"11","N02_002":"2","N02_003":"???","N02_004":"???????"}},
{"type":"Feature","geometry":{"type":"LineString","coordinates":[[138.66018,37.35732],[138.6536,37.35629],[138.64419,37.34944],[138.64223,37.34448],[138.63757,37.33892]]},"properties":{"N02_001":"11","N02_002":"2","N02_003":"???","N02_004":"???????"}},
{"type":"Feature","geometry":{"type":"LineString","coordinates":[[138.32449,37.22258],[138.31681,37.21765]]},"properties":{"N02_001":"11","N02_002":"2","N02_003":"???","N02_004":"???????"}},
{"type":"Feature","geometry":{"type":"LineString","coordinates":[[138.5548,37.36333],[138.55804,37.36378]]},"properties":{"N02_001":"11","N02_002":"2","N02_003":"???","N02_004":"???????"}},
{"type":"Feature","geometry":{"type":"LineString","coordinates":[[138.43057,37.31617],[138.42427,37.31132],[138.4099,37.29829],[138.38645,37.27849]]},"properties":{"N02_001":"11","N02_002":"2","N02_003":"???","N02_004":"???????"}},
{"type":"Feature","geometry":{"type":"LineString","coordinates":[[138.26912,37.18514],[138.2745,37.1907],[138.30433,37.2097]]},"properties":{"N02_001":"11","N02_002":"2","N02_003":"???","N02_004":"???????"}},
{"type":"Feature","geometry":{"type":"LineString","coordinates":[[138.46623,37.33557],[138.46171,37.3346],[138.44936,37.32371],[138.44609,37.32272],[138.43936,37.3231],[138.43235,37.31754]]},"properties":{"N02_001":"11","N02_002":"2","N02_003":"???","N02_004":"???????"}},
{"type":"Feature","geometry":{"type":"LineString","coordinates":[[138.26759,37.18335],[138.26912,37.18514]]},"properties":{"N02_001":"11","N02_002":"2","N02_003":"???","N02_004":"???????"}},
{"type":"Feature","geometry":{"type":"LineString","coordinates":[[138.36106,37.25188],[138.34065,37.23484]]},"properties":{"N02_001":"11","N02_002":"2","N02_003":"???","N02_004":"???????"}},
{"type":"Feature","geometry":{"type":"LineString","coordinates":[[138.38645,37.27849],[138.38539,37.27707]]},"properties":{"N02_001":"11","N02_002":"2","N02_003":"???","N02_004":"???????"}},
{"type":"Feature","geometry":{"type":"LineString","coordinates":[[138.68461,37.36598],[138.6836,37.36686]]},"properties":{"N02_001":"11","N02_002":"2","N02_003":"???","N02_004":"???????"}},
{"type":"Feature","geometry":{"type":"LineString","coordinates":[[138.7289,37.35467],[138.71931,37.35143],[138.71048,37.3522],[138.69801,37.35723],[138.69179,37.3606],[138.68461,37.36598]]},"properties":{"N02_001":"11","N02_002":"2","N02_003":"???","N02_004":"???????"}},
{"type":"Feature","geometry":{"type":"LineString","coordinates":[[138.61173,37.34147],[138.6126,37.34078]]},"properties":{"N02_001":"11","N02_002":"2","N02_003":"???","N02_004":"???????"}},
{"type":"Feature","geometry":{"type":"LineString","coordinates":[[138.2436,37.17106],[138.24673,37.17282]]},"properties":{"N02_001":"11","N02_002":"2","N02_003":"???","N02_004":"???????"}},
{"type":"Feature","geometry":{"type":"LineString","coordinates":[[138.2436,37.17106],[138.24087,37.16945]]},"properties":{"N02_001":"11","N02_002":"2","N02_003":"???","N02_004":"???????"}},
{"type":"Feature","geometry":{"type":"LineString","coordinates":[[138.30559,37.2105],[138.30925,37.21289]]},"properties":{"N02_001":"11","N02_002":"2","N02_003":"???","N02_004":"???????"}},
{"type":"Feature","geometry":{"type":"LineString","coordinates":[[138.30925,37.21289],[138.31063,37.21397]]},"properties":{"N02_001":"11","N02_002":"2","N02_003":"???","N02_004":"???????"}},
{"type":"Feature","geometry":{"type":"LineString","coordinates":[[138.30433,37.2097],[138.30559,37.2105]]},"properties":{"N02_001":"11","N02_002":"2","N02_003":"???","N02_004":"???????"}},
{"type":"Feature","geometry":{"type":"LineString","coordinates":[[138.14521,36.59522],[138.14495,36.59454]]},"properties":{"N02_001":"11","N02_002":"2","N02_003":"???","N02_004":"???????"}},
{"type":"Feature","geometry":{"type":"LineString","coordinates":[[138.16138,36.63003],[138.15519,36.62657],[138.15342,36.62411],[138.15089,36.61498]]},"properties":{"N02_001":"11","N02_002":"2","N02_003":"???","N02_004":"???????"}},
{"type":"Feature","geometry":{"type":"LineString","coordinates":[[138.16226,36.63051],[138.16138,36.63003]]},"properties":{"N02_001":"11","N02_002":"2","N02_003":"???","N02_004":"???????"}},
{"type":"Feature","geometry":{"type":"LineString","coordinates":[[138.14495,36.59454],[138.13861,36.5784]]},"properties":{"N02_001":"11","N02_002":"2","N02_003":"???","N02_004":"???????"}},
{"type":"Feature","geometry":{"type":"LineString","coordinates":[[138.15051,36.6132],[138.14852,36.60377],[138.14521,36.59522]]},"properties":{"N02_001":"11","N02_002":"2","N02_003":"???","N02_004":"???????"}},
{"type":"Feature","geometry":{"type":"LineString","coordinates":[[138.18778,36.64276],[138.18239,36.63937],[138.17325,36.63674],[138.16226,36.63051]]},"properties":{"N02_001":"11","N02_002":"2","N02_003":"???","N02_004":"???????"}},
{"type":"Feature","geometry":{"type":"LineString","coordinates":[[138.15089,36.61498],[138.15051,36.6132]]},"properties":{"N02_001":"11","N02_002":"2","N02_003":"???","N02_004":"???????"}},
{"type":"Feature","geometry":{"type":"LineString","coordinates":[[139.01249,36.32059],[139.01219,36.32395]]},"properties":{"N02_001":"11","N02_002":"2","N02_003":"???","N02_004":"???????"}},
{"type":"Feature","geometry":{"type":"LineString","coordinates":[[138.85067,36.29839],[138.85719,36.29869],[138.86755,36.30241],[138.87144,36.30469],[138.88585,36.31452],[138.90037,36.32387],[138.91017,36.33119],[138.91339,36.33163]]},"properties":{"N02_001":"11","N02_002":"2","N02_003":"???","N02_004":"???????"}},
{"type":"Feature","geometry":{"type":"LineString","coordinates":[[138.95872,36.33767],[138.97387,36.33802],[138.97848,36.33885]]},"properties":{"N02_001":"11","N02_002":"2","N02_003":"???","N02_004":"???????"}},
{"type":"Feature","geometry":{"type":"LineString","coordinates":[[138.85067,36.29839],[138.84868,36.29835]]},"properties":{"N02_001":"11","N02_002":"2","N02_003":"???","N02_004":"???????"}},
{"type":"Feature","geometry":{"type":"LineString","coordinates":[[138.84868,36.29835],[138.84355,36.29818],[138.8321,36.29627],[138.82193,36.29763],[138.81854,36.29865],[138.80704,36.30472],[138.79805,36.3089]]},"properties":{"N02_001":"11","N02_002":"2","N02_003":"???","N02_004":"???????"}},
{"type":"Feature","geometry":{"type":"LineString","coordinates":[[138.97848,36.33885],[138.986,36.34014]]},"properties":{"N02_001":"11","N02_002":"2","N02_003":"???","N02_004":"???????"}},
{"type":"Feature","geometry":{"type":"LineString","coordinates":[[139.01219,36.32395],[139.01214,36.32452]]},"properties":{"N02_001":"11","N02_002":"2","N02_003":"???","N02_004":"???????"}},
{"type":"Feature","geometry":{"type":"LineString","coordinates":[[139.01214,36.32452],[139.01163,36.33408],[139.00879,36.33648],[139.0036,36.33811]]},"properties":{"N02_001":"11","N02_002":"2","N02_003":"???","N02_004":"???????"}},
{"type":"Feature","geometry":{"type":"LineString","coordinates":[[138.79726,36.30941],[138.78698,36.31585]]},"properties":{"N02_001":"11","N02_002":"2","N02_003":"???","N02_004":"???????"}},
{"type":"Feature","geometry":{"type":"LineString","coordinates":[[138.95626,36.33765],[138.93689,36.33782],[138.93236,36.33325],[138.92901,36.33205],[138.91558,36.33168]]},"properties":{"N02_001":"11","N02_002":"2","N02_003":"???","N02_004":"???????"}},
{"type":"Feature","geometry":{"type":"LineString","coordinates":[[138.78698,36.31585],[138.78628,36.31631]]},"properties":{"N02_001":"11","N02_002":"2","N02_003":"???","N02_004":"???????"}},
{"type":"Feature","geometry":{"type":"LineString","coordinates":[[139.00117,36.33889],[138.99728,36.33985],[138.986,36.34014]]},"properties":{"N02_001":"11","N02_002":"2","N02_003":"???","N02_004":"???????"}},
{"type":"Feature","geometry":{"type":"LineString","coordinates":[[139.0036,36.33811],[139.00117,36.33889]]},"properties":{"N02_001":"11","N02_002":"2","N02_003":"???","N02_004":"???????"}},
{"type":"Feature","geometry":{"type":"LineString","coordinates":[[138.79805,36.3089],[138.79726,36.30941]]},"properties":{"N02_001":"11","N02_002":"2","N02_003":"???","N02_004":"???????"}},
{"type":"Feature","geometry":{"type":"LineString","coordinates":[[138.95872,36.33767],[138.95626,36.33765]]},"properties":{"N02_001":"11","N02_002":"2","N02_003":"???","N02_004":"???????"}},
{"type":"Feature","geometry":{"type":"LineString","coordinates":[[138.91339,36.33163],[138.91558,36.33168]]},"properties":{"N02_001":"11","N02_002":"2","N02_003":"???","N02_004":"???????"}},
{"type":"Feature","geometry":{"type":"LineString","coordinates":[[138.97848,36.33885],[138.986,36.34014]]},"properties":{"N02_001":"11","N02_002":"2","N02_003":"???","N02_004":"???????"}},
{"type":"Feature","geometry":{"type":"LineString","coordinates":[[138.13765,36.57581],[138.13861,36.5784]]},"properties":{"N02_001":"11","N02_002":"2","N02_003":"???","N02_004":"???????"}},
{"type":"Feature","geometry":{"type":"LineString","coordinates":[[138.73647,36.33604],[138.7365,36.33613]]},"properties":{"N02_001":"11","N02_002":"2","N02_003":"???","N02_004":"???????"}},
{"type":"Feature","geometry":{"type":"LineString","coordinates":[[138.78628,36.31631],[138.7796,36.32032],[138.77304,36.32118],[138.76742,36.32445],[138.7582,36.32663],[138.74808,36.33369],[138.7393,36.33581]]},"properties":{"N02_001":"11","N02_002":"2","N02_003":"???","N02_004":"???????"}},
{"type":"Feature","geometry":{"type":"LineString","coordinates":[[138.7365,36.33613],[138.7393,36.33581]]},"properties":{"N02_001":"11","N02_002":"2","N02_003":"???","N02_004":"???????"}},
{"type":"Feature","geometry":{"type":"LineString","coordinates":[[138.18992,36.64416],[138.18778,36.64276]]},"properties":{"N02_001":"11","N02_002":"2","N02_003":"???","N02_004":"???????"}}
]}