{"type":"FeatureCollection","features":[
{"type":"Feature","geometry":{"type":"LineString","coordinates":[[141.30269,38.43537],[141.30447,38.43534]]},"properties":{"N02_001":"11","N02_002":"2","N02_003":"???","N02_004":"???????"}},
{"type":"Feature","geometry":{"type":"LineString","coordinates":[[141.28845,38.43763],[141.28922,38.43782]]},"properties":{"N02_001":"11","N02_002":"2","N02_003":"???","N02_004":"???????"}},
{"type":"Feature","geometry":{"type":"LineString","coordinates":[[141.27808,38.43806],[141.28398,38.43659],[141.28845,38.43763]]},"properties":{"N02_001":"11","N02_002":"2","N02_003":"???","N02_004":"???????"}},
{"type":"Feature","geometry":{"type":"LineString","coordinates":[[141.23953,38.43251],[141.23846,38.43232]]},"properties":{"N02_001":"11","N02_002":"2","N02_003":"???","N02_004":"???????"}},
{"type":"Feature","geometry":{"type":"LineString","coordinates":[[141.27808,38.43806],[141.27726,38.43839]]},"properties":{"N02_001":"11","N02_002":"2","N02_003":"???","N02_004":"???????"}},
{"type":"Feature","geometry":{"type":"LineString","coordinates":[[141.28922,38.43782],[141.29273,38.43861],[141.29616,38.43821]]},"properties":{"N02_001":"11","N02_002":"2","N02_003":"???","N02_004":"???????"}},
{"type":"Feature","geometry":{"type":"LineString","coordinates":[[141.29616,38.43821],[141.3003,38.43563],[141.30269,38.43537]]},"properties":{"N02_001":"11","N02_002":"2","N02_003":"???","N02_004":"???????"}},
{"type":"Feature","geometry":{"type":"LineString","coordinates":[[141.27726,38.43839],[141.2752,38.43875],[141.23953,38.43251]]},"properties":{"N02_001":"11","N02_002":"2","N02_003":"???","N02_004":"???????"}},
{"type":"Feature","geometry":{"type":"LineString","coordinates":[[141.22286,38.42822],[141.2217,38.42777]]},"properties":{"N02_001":"11","N02_002":"2","N02_003":"???","N02_004":"???????"}},
{"type":"Feature","geometry":{"type":"LineString","coordinates":[[141.23846,38.43232],[141.22939,38.43073],[141.22286,38.42822]]},"properties":{"N02_001":"11","N02_002":"2","N02_003":"???","N02_004":"???????"}},
{"type":"Feature","geometry":{"type":"LineString","coordinates":[[141.2217,38.42777],[141.21463,38.42496],[141.20956,38.42089]]},"properties":{"N02_001":"11","N02_002":"2","N02_003":"???","N02_004":"???????"}},
{"type":"Feature","geometry":{"type":"LineString","coordinates":[[141.20956,38.42089],[141.20872,38.42008]]},"properties":{"N02_001":"11","N02_002":"2","N02_003":"???","N02_004":"???????"}},
{"type":"Feature","geometry":{"type":"LineString","coordinates":[[140.96711,38.27332],[140.96813,38.27368]]},"properties":{"N02_001":"11","N02_002":"2","N02_003":"???","N02_004":"???????"}},
{"type":"Feature","geometry":{"type":"LineString","coordinates":[[141.01505,38.30537],[141.01524,38.30107],[141.01094,38.29475],[141.00585,38.29178]]},"properties":{"N02_001":"11","N02_002":"2","N02_003":"???","N02_004":"???????"}},
{"type":"Feature","geometry":{"type":"LineString","coordinates":[[140.9112,38.26618],[140.91856,38.26837]]},"properties":{"N02_001":"11","N02_002":"2","N02_003":"???","N02_004":"???????"}},
{"type":"Feature","geometry":{"type":"LineString","coordinates":[[141.17522,38.39615],[141.17433,38.3959]]},"properties":{"N02_001":"11","N02_002":"2","N02_003":"???","N02_004":"???????"}},
{"type":"Feature","geometry":{"type":"LineString","coordinates":[[140.89425,38.25869],[140.89942,38.2581],[140.90444,38.26036]]},"properties":{"N02_001":"11","N02_002":"2","N02_003":"???","N02_004":"???????"}},
{"type":"Feature","geometry":{"type":"LineString","coordinates":[[141.07331,38.38256],[141.07056,38.37967],[141.06106,38.37644],[141.05751,38.37248],[141.05866,38.36868]]},"properties":{"N02_001":"11","N02_002":"2","N02_003":"???","N02_004":"???????"}},
{"type":"Feature","geometry":{"type":"LineString","coordinates":[[140.88373,38.26032],[140.88456,38.26004]]},"properties":{"N02_001":"11","N02_002":"2","N02_003":"???","N02_004":"???????"}},
{"type":"Feature","geometry":{"type":"LineString","coordinates":[[140.91856,38.26837],[140.91941,38.26917]]},"properties":{"N02_001":"11","N02_002":"2","N02_003":"???","N02_004":"???????"}},
{"type":"Feature","geometry":{"type":"LineString","coordinates":[[141.20872,38.42008],[141.19046,38.40361]]},"properties":{"N02_001":"11","N02_002":"2","N02_003":"???","N02_004":"???????"}},
{"type":"Feature","geometry":{"type":"LineString","coordinates":[[141.03126,38.32536],[141.02976,38.3238],[141.02505,38.32156],[141.02285,38.31801]]},"properties":{"N02_001":"11","N02_002":"2","N02_003":"???","N02_004":"???????"}},
{"type":"Feature","geometry":{"type":"LineString","coordinates":[[140.88456,38.26004],[140.89335,38.25881]]},"properties":{"N02_001":"11","N02_002":"2","N02_003":"???","N02_004":"???????"}},
{"type":"Feature","geometry":{"type":"LineString","coordinates":[[141.03208,38.3259],[141.03126,38.32536]]},"properties":{"N02_001":"11","N02_002":"2","N02_003":"???","N02_004":"???????"}},
{"type":"Feature","geometry":{"type":"LineString","coordinates":[[140.93428,38.27335],[140.93563,38.27344]]},"properties":{"N02_001":"11","N02_002":"2","N02_003":"???","N02_004":"???????"}},
{"type":"Feature","geometry":{"type":"LineString","coordinates":[[141.07379,38.38309],[141.07331,38.38256]]},"properties":{"N02_001":"11","N02_002":"2","N02_003":"???","N02_004":"???????"}},
{"type":"Feature","geometry":{"type":"LineString","coordinates":[[141.19046,38.40361],[141.18974,38.40295]]},"properties":{"N02_001":"11","N02_002":"2","N02_003":"???","N02_004":"???????"}},
{"type":"Feature","geometry":{"type":"LineString","coordinates":[[141.1296,38.37886],[141.12877,38.37917]]},"properties":{"N02_001":"11","N02_002":"2","N02_003":"???","N02_004":"???????"}},
{"type":"Feature","geometry":{"type":"LineString","coordinates":[[141.12877,38.37917],[141.11588,38.38173],[141.10756,38.38608]]},"properties":{"N02_001":"11","N02_002":"2","N02_003":"???","N02_004":"???????"}},
{"type":"Feature","geometry":{"type":"LineString","coordinates":[[140.93563,38.27344],[140.95775,38.27499]]},"properties":{"N02_001":"11","N02_002":"2","N02_003":"???","N02_004":"???????"}},
{"type":"Feature","geometry":{"type":"LineString","coordinates":[[141.01854,38.31232],[141.0182,38.31159]]},"properties":{"N02_001":"11","N02_002":"2","N02_003":"???","N02_004":"???????"}},
{"type":"Feature","geometry":{"type":"LineString","coordinates":[[140.91941,38.26917],[140.92092,38.27146],[140.92616,38.27275],[140.93428,38.27335]]},"properties":{"N02_001":"11","N02_002":"2","N02_003":"???","N02_004":"???????"}},
{"type":"Feature","geometry":{"type":"LineString","coordinates":[[141.10756,38.38608],[141.10697,38.38652]]},"properties":{"N02_001":"11","N02_002":"2","N02_003":"???","N02_004":"???????"}},
{"type":"Feature","geometry":{"type":"LineString","coordinates":[[141.09318,38.38723],[141.09229,38.38697]]},"properties":{"N02_001":"11","N02_002":"2","N02_003":"???","N02_004":"???????"}},
{"type":"Feature","geometry":{"type":"LineString","coordinates":[[140.90444,38.26036],[140.905,38.26092]]},"properties":{"N02_001":"11","N02_002":"2","N02_003":"???","N02_004":"???????"}},
{"type":"Feature","geometry":{"type":"LineString","coordinates":[[140.98595,38.28119],[140.99505,38.28595],[140.99967,38.29038],[141.00491,38.29158]]},"properties":{"N02_001":"11","N02_002":"2","N02_003":"???","N02_004":"???????"}},
{"type":"Feature","geometry":{"type":"LineString","coordinates":[[141.04134,38.3504],[141.03745,38.34517],[141.03599,38.33973],[141.03647,38.33478],[141.03594,38.33012],[141.03208,38.3259]]},"properties":{"N02_001":"11","N02_002":"2","N02_003":"???","N02_004":"???????"}},
{"type":"Feature","geometry":{"type":"LineString","coordinates":[[140.96813,38.27368],[140.97605,38.27656],[140.98465,38.2805]]},"properties":{"N02_001":"11","N02_002":"2","N02_003":"???","N02_004":"???????"}},
{"type":"Feature","geometry":{"type":"LineString","coordinates":[[141.09229,38.38697],[141.08565,38.38546],[141.07583,38.38453],[141.07379,38.38309]]},"properties":{"N02_001":"11","N02_002":"2","N02_003":"???","N02_004":"???????"}},
{"type":"Feature","geometry":{"type":"LineString","coordinates":[[140.905,38.26092],[140.90773,38.2646],[140.91034,38.26597]]},"properties":{"N02_001":"11","N02_002":"2","N02_003":"???","N02_004":"???????"}},
{"type":"Feature","geometry":{"type":"LineString","coordinates":[[140.89335,38.25881],[140.89425,38.25869]]},"properties":{"N02_001":"11","N02_002":"2","N02_003":"???","N02_004":"???????"}},
{"type":"Feature","geometry":{"type":"LineString","coordinates":[[140.91034,38.26597],[140.9112,38.26618]]},"properties":{"N02_001":"11","N02_002":"2","N02_003":"???","N02_004":"???????"}},
{"type":"Feature","geometry":{"type":"LineString","coordinates":[[141.10697,38.38652],[141.10498,38.38756],[141.09318,38.38723]]},"properties":{"N02_001":"11","N02_002":"2","N02_003":"???","N02_004":"???????"}},
{"type":"Feature","geometry":{"type":"LineString","coordinates":[[141.02285,38.31801],[141.02209,38.31742]]},"properties":{"N02_001":"11","N02_002":"2","N02_003":"???","N02_004":"???????"}},
{"type":"Feature","geometry":{"type":"LineString","coordinates":[[141.01494,38.3063],[141.01505,38.30537]]},"properties":{"N02_001":"11","N02_002":"2","N02_003":"???","N02_004":"???????"}},
{"type":"Feature","geometry":{"type":"LineString","coordinates":[[141.0182,38.31159],[141.01494,38.3063]]},"properties":{"N02_001":"11","N02_002":"2","N02_003":"???","N02_004":"???????"}},
{"type":"Feature","geometry":{"type":"LineString","coordinates":[[141.05902,38.36806],[141.0595,38.36495],[141.05796,38.36231],[141.05226,38.35837],[141.04703,38.35751],[141.04248,38.35476],[141.04199,38.35131]]},"properties":{"N02_001":"11","N02_002":"2","N02_003":"???","N02_004":"???????"}},
{"type":"Feature","geometry":{"type":"LineString","coordinates":[[140.87895,38.26071],[140.88373,38.26032]]},"properties":{"N02_001":"11","N02_002":"2","N02_003":"???","N02_004":"???????"}},
{"type":"Feature","geometry":{"type":"LineString","coordinates":[[140.98465,38.2805],[140.98595,38.28119]]},"properties":{"N02_001":"11","N02_002":"2","N02_003":"???","N02_004":"???????"}},
{"type":"Feature","geometry":{"type":"LineString","coordinates":[[141.18974,38.40295],[141.18564,38.39954],[141.17522,38.39615]]},"properties":{"N02_001":"11","N02_002":"2","N02_003":"???","N02_004":"???????"}},
{"type":"Feature","geometry":{"type":"LineString","coordinates":[[141.02209,38.31742],[141.01854,38.31232]]},"properties":{"N02_001":"11","N02_002":"2","N02_003":"???","N02_004":"???????"}},
{"type":"Feature","geometry":{"type":"LineString","coordinates":[[140.87809,38.26057],[140.87895,38.26071]]},"properties":{"N02_001":"11","N02_002":"2","N02_003":"???","N02_004":"???????"}},
{"type":"Feature","geometry":{"type":"LineString","coordinates":[[141.04199,38.35131],[141.04134,38.3504]]},"properties":{"N02_001":"11","N02_002":"2","N02_003":"???","N02_004":"???????"}},
{"type":"Feature","geometry":{"type":"LineString","coordinates":[[140.95775,38.27499],[140.95882,38.27495]]},"properties":{"N02_001":"11","N02_002":"2","N02_003":"???","N02_004":"???????"}},
{"type":"Feature","geometry":{"type":"LineString","coordinates":[[141.05866,38.36868],[141.05902,38.36806]]},"properties":{"N02_001":"11","N02_002":"2","N02_003":"???","N02_004":"???????"}},
{"type":"Feature","geometry":{"type":"LineString","coordinates":[[140.95882,38.27495],[140.96526,38.27309],[140.96711,38.27332]]},"properties":{"N02_001":"11","N02_002":"2","N02_003":"???","N02_004":"???????"}},
{"type":"Feature","geometry":{"type":"LineString","coordinates":[[141.00585,38.29178],[141.00491,38.29158]]},"properties":{"N02_001":"11","N02_002":"2","N02_003":"???","N02_004":"???????"}},
{"type":"Feature","geometry":{"type":"LineString","coordinates":[[141.17433000000017,38.3959000000001],[141.16979570442538,38.39402271027427],[141.1620719739991,38.38702709491599],[141.1602017176483,38.38098802288226],[141.15696089175776,38.37911776653141]]},"properties":{"N02_001":"11","N02_002":"2","N02_003":"???","N02_004":"???????"}},
{"type":"Feature","geometry":{"type":"LineString","coordinates":[[141.15696089175776,38.37911776653141],[141.15618994639192,38.378675186784164]]},"properties":{"N02_001":"11","N02_002":"2","N02_003":"???","N02_004":"???????"}},
{"type":"Feature","geometry":{"type":"LineString","coordinates":[[141.15618994639192,38.378675186784164],[141.1508076055959,38.375891217407],[141.14426884675083,38.375277316467304]]},"properties":{"N02_001":"11","N02_002":"2","N02_003":"???","N02_004":"???????"}},
{"type":"Feature","geometry":{"type":"LineString","coordinates":[[141.14426884675095,38.375277316467304],[141.14359783874693,38.375291593233385]]},"properties":{"N02_001":"11","N02_002":"2","N02_003":"???","N02_004":"???????"}},
{"type":"Feature","geometry":{"type":"LineString","coordinates":[[141.14359783874693,38.375291593233385],[141.13951468366042,38.375891217407],[141.12959999999998,38.37886000000009]]},"properties":{"N02_001":"11","N02_002":"2","N02_003":"???","N02_004":"???????"}}
]}